azure_doc_processing/__init__.py
azure_doc_processing/blob_storage.py
azure_doc_processing/document_intelligence.py
azure_doc_processing/keyvault.py
azure_doc_processing/logger.py
azure_doc_processing/openai_service.py
azure_doc_processing/table_storage.py
azure_doc_processing/utils.py
azure_doc_processing-1.1.2.dist-info/LICENSE
azure_doc_processing-1.1.2.dist-info/METADATA
azure_doc_processing-1.1.2.dist-info/NOTICE
azure_doc_processing-1.1.2.dist-info/WHEEL
azure_doc_processing-1.1.2.dist-info/RECORD
