Metadata-Version: 2.1
Name: azure-doc-processing
Version: 1.1.2
Summary: Utilities for Azure document processing
Home-page: https://github.com/Verdel-Digitaal-Partner/azure-doc-processing
License: Apache-2.0
Keywords: azure,document,processing,nlp,openai,blob,keyvault
Author: Bas van der Laan
Author-email: b.vanderlaan@verdel.nl
Requires-Python: >=3.10,<3.14
Classifier: License :: OSI Approved :: Apache Software License
Classifier: Operating System :: OS Independent
Classifier: Programming Language :: Python :: 3
Classifier: Programming Language :: Python :: 3.10
Classifier: Programming Language :: Python :: 3.11
Classifier: Programming Language :: Python :: 3.12
Classifier: Programming Language :: Python :: 3.13
Requires-Dist: azure-ai-documentintelligence (>=1.0.2,<2.0.0)
Requires-Dist: azure-data-tables (>=12.7.0,<13.0.0)
Requires-Dist: azure-identity (>=1.23.0,<2.0.0)
Requires-Dist: azure-keyvault (>=4.2.0,<5.0.0)
Requires-Dist: azure-storage-blob (>=12.19,<13.0)
Requires-Dist: langchain-openai (>=0.3.24,<0.4.0)
Requires-Dist: openai (>=1.55.3,<2.0.0)
Requires-Dist: pandas (>=2.3,<3.0)
Requires-Dist: pypdf (>=5.6.1,<6.0.0)
Requires-Dist: pytz (>=2023.3)
Project-URL: Documentation, https://github.com/Verdel-Digitaal-Partner/azure-doc-processing#readme
Project-URL: Repository, https://github.com/Verdel-Digitaal-Partner/azure-doc-processing
